mozzarella/__init__.py
mozzarella-0.1.1.dist-info/METADATA
mozzarella-0.1.1.dist-info/WHEEL
mozzarella-0.1.1.dist-info/top_level.txt
mozzarella-0.1.1.dist-info/RECORD
