Metadata-Version: 2.1
Name: mozzarella
Version: 0.1.1
Summary: Use procedural macros in Python
Requires-Python: >=3.11
